rag_select/__init__.py
rag_select/rag_client.py
rag_select/registry.py
rag_select/experiment/__init__.py
rag_select/experiment/metrics.py
rag_select/experiment/pipeline.py
rag_select/experiment/rag_experiment.py
rag_select/experiment/results.py
rag_select/experiment/artifact/__init__.py
rag_select/experiment/artifact/rag_artifact.py
rag_select/experiment/rag_client/__init__.py
rag_select/experiment/rag_client/registry.py
rag_select/experiment/rag_client/parameter_impls/__init__.py
rag_select/experiment/rag_client/parameter_impls/chunking_impls/__init__.py
rag_select/experiment/rag_client/parameter_impls/chunking_impls/chunking_base.py
rag_select/experiment/rag_client/parameter_impls/chunking_impls/langchain_recursive.py
rag_select/experiment/rag_client/parameter_impls/chunking_impls/langchain_token.py
rag_select/experiment/rag_client/parameter_impls/chunking_impls/llamaindex_sentence.py
rag_select/experiment/rag_client/parameter_impls/chunking_impls/sliding_window.py
rag_select/experiment/rag_client/parameter_impls/embedding_impls/__init__.py
rag_select/experiment/rag_client/parameter_impls/embedding_impls/cohere_embedding.py
rag_select/experiment/rag_client/parameter_impls/embedding_impls/embedding_base.py
rag_select/experiment/rag_client/parameter_impls/embedding_impls/huggingface_embedding.py
rag_select/experiment/rag_client/parameter_impls/embedding_impls/openai_embedding.py
rag_select/experiment/rag_client/parameter_impls/embedding_impls/simple_embedding.py
rag_select/experiment/rag_client/parameter_impls/embedding_impls/voyage_embedding.py
rag_select/experiment/rag_client/parameter_impls/ingestion_impls/__init__.py
rag_select/experiment/rag_client/parameter_impls/ingestion_impls/docling.py
rag_select/experiment/rag_client/parameter_impls/ingestion_impls/ingestion_base.py
rag_select/experiment/rag_client/parameter_impls/ingestion_impls/llamaparse_ingestion.py
rag_select/experiment/rag_client/parameter_impls/ingestion_impls/simple_ingestion.py
rag_select-0.1.3.dist-info/METADATA
rag_select-0.1.3.dist-info/WHEEL
rag_select-0.1.3.dist-info/top_level.txt
rag_select-0.1.3.dist-info/RECORD
